UserAgentReplica/__init__.py
UserAgentReplica/main.py
UserAgentReplica-1.1.1.dist-info/METADATA
UserAgentReplica-1.1.1.dist-info/WHEEL
UserAgentReplica-1.1.1.dist-info/top_level.txt
UserAgentReplica-1.1.1.dist-info/RECORD
