Metadata-Version: 2.1
Name: UserAgentReplica
Version: 1.1.1
Summary: Generates safe and dummy usable user agent and xms user agent
Home-page: https://github.com/Prime-Hritu/UserAgentReplica
Author: Pʀɪᴍᴇ Hʀɪᴛᴜ
Project-URL: GitHub, https://github.com/Prime-Hritu/UserAgentReplica
